AUTHORS.txt
LICENSE.txt
MANIFEST.in
README.rst
setup.cfg
setup.py
django_gipsy.egg-info/PKG-INFO
django_gipsy.egg-info/SOURCES.txt
django_gipsy.egg-info/dependency_links.txt
django_gipsy.egg-info/pbr.json
django_gipsy.egg-info/requires.txt
django_gipsy.egg-info/top_level.txt
gipsy/__init__.py
gipsy/admin.py
gipsy/models.py
gipsy/dashboard/__init__.py
gipsy/dashboard/admin.py
gipsy/dashboard/apps.py
gipsy/dashboard/dashboard.py
gipsy/dashboard/models.py
gipsy/dashboard/settings.py
gipsy/dashboard/migrations/0001_initial.py
gipsy/dashboard/migrations/0002_auto_20170724_1532.py
gipsy/dashboard/migrations/__init__.py
gipsy/dashboard/presets/__init__.py
gipsy/dashboard/presets/default.py
gipsy/dashboard/presets/google_analytics.py
gipsy/dashboard/services/__init__.py
gipsy/dashboard/services/google_analytics_connector.py
gipsy/dashboard/static/gipsy_dashboard/css/.gitkeep
gipsy/dashboard/static/gipsy_dashboard/css/bootstrap.css
gipsy/dashboard/static/gipsy_dashboard/css/custom.css
gipsy/dashboard/static/gipsy_dashboard/css/gipsy.css
gipsy/dashboard/static/gipsy_dashboard/css/main.css
gipsy/dashboard/static/gipsy_dashboard/css/bootstrap/bootstrap.css
gipsy/dashboard/static/gipsy_dashboard/css/fontawesome/font-awesome.css
gipsy/dashboard/static/gipsy_dashboard/css/fontawesome/scss/font-awesome.css
gipsy/dashboard/static/gipsy_dashboard/fonts/bootstrap/glyphicons-halflings-regular.eot
gipsy/dashboard/static/gipsy_dashboard/fonts/bootstrap/glyphicons-halflings-regular.svg
gipsy/dashboard/static/gipsy_dashboard/fonts/bootstrap/glyphicons-halflings-regular.ttf
gipsy/dashboard/static/gipsy_dashboard/fonts/bootstrap/glyphicons-halflings-regular.woff
gipsy/dashboard/static/gipsy_dashboard/fonts/fontawesome/FontAwesome.otf
gipsy/dashboard/static/gipsy_dashboard/fonts/fontawesome/fontawesome-webfont.eot
gipsy/dashboard/static/gipsy_dashboard/fonts/fontawesome/fontawesome-webfont.svg
gipsy/dashboard/static/gipsy_dashboard/fonts/fontawesome/fontawesome-webfont.ttf
gipsy/dashboard/static/gipsy_dashboard/fonts/fontawesome/fontawesome-webfont.woff
gipsy/dashboard/static/gipsy_dashboard/img/.gitkeep
gipsy/dashboard/static/gipsy_dashboard/img/bg_body-01.jpg
